README.txt
setup.cfg
setup.py
Minimatic.egg-info/PKG-INFO
Minimatic.egg-info/SOURCES.txt
Minimatic.egg-info/dependency_links.txt
Minimatic.egg-info/not-zip-safe
Minimatic.egg-info/requires.txt
Minimatic.egg-info/top_level.txt
minimatic/__init__.py
minimatic/jsmin.py