Metadata-Version: 1.0
Name: Minimatic
Version: 1.0
Summary: CSS and Javascript Minification/Combination Upgrade to WebHelpers
Home-page: UNKNOWN
Author: Linas Juskevicius
Author-email: linas@idiles.com
License: UNKNOWN
Platform: UNKNOWN
